LICENSE
README.md
setup.py
DependencyParser/DependencyRelation.c
DependencyParser/DependencyRelation.pxd
DependencyParser/DependencyRelation.pyx
DependencyParser/ParserEvaluationScore.c
DependencyParser/ParserEvaluationScore.pxd
DependencyParser/ParserEvaluationScore.pyx
DependencyParser/__init__.py
DependencyParser/Stanford/StanfordDependencyRelation.c
DependencyParser/Stanford/StanfordDependencyRelation.pxd
DependencyParser/Stanford/StanfordDependencyRelation.pyx
DependencyParser/Stanford/StanfordDependencyType.py
DependencyParser/Stanford/__init__.py
DependencyParser/Turkish/TurkishDependencyRelation.c
DependencyParser/Turkish/TurkishDependencyRelation.pxd
DependencyParser/Turkish/TurkishDependencyRelation.pyx
DependencyParser/Turkish/TurkishDependencyTreeBankCorpus.c
DependencyParser/Turkish/TurkishDependencyTreeBankCorpus.pyx
DependencyParser/Turkish/TurkishDependencyTreeBankSentence.c
DependencyParser/Turkish/TurkishDependencyTreeBankSentence.pxd
DependencyParser/Turkish/TurkishDependencyTreeBankSentence.pyx
DependencyParser/Turkish/TurkishDependencyTreeBankWord.c
DependencyParser/Turkish/TurkishDependencyTreeBankWord.pxd
DependencyParser/Turkish/TurkishDependencyTreeBankWord.pyx
DependencyParser/Turkish/TurkishDependencyType.py
DependencyParser/Turkish/__init__.py
DependencyParser/Universal/UniversalDependencyPosType.py
DependencyParser/Universal/UniversalDependencyRelation.c
DependencyParser/Universal/UniversalDependencyRelation.pxd
DependencyParser/Universal/UniversalDependencyRelation.pyx
DependencyParser/Universal/UniversalDependencyTreeBankCorpus.c
DependencyParser/Universal/UniversalDependencyTreeBankCorpus.pxd
DependencyParser/Universal/UniversalDependencyTreeBankCorpus.pyx
DependencyParser/Universal/UniversalDependencyTreeBankFeatures.c
DependencyParser/Universal/UniversalDependencyTreeBankFeatures.pxd
DependencyParser/Universal/UniversalDependencyTreeBankFeatures.pyx
DependencyParser/Universal/UniversalDependencyTreeBankSentence.c
NlpToolkit_DependencyParser_Cy.egg-info/PKG-INFO
NlpToolkit_DependencyParser_Cy.egg-info/SOURCES.txt
NlpToolkit_DependencyParser_Cy.egg-info/dependency_links.txt
NlpToolkit_DependencyParser_Cy.egg-info/requires.txt
NlpToolkit_DependencyParser_Cy.egg-info/top_level.txt
nlptoolkit_dependencyparser_cy.egg-info/PKG-INFO
nlptoolkit_dependencyparser_cy.egg-info/SOURCES.txt
nlptoolkit_dependencyparser_cy.egg-info/dependency_links.txt
nlptoolkit_dependencyparser_cy.egg-info/requires.txt
nlptoolkit_dependencyparser_cy.egg-info/top_level.txt