Metadata-Version: 2.4
Name: nlptoolkit-dependencyparser-cy
Version: 1.0.16
Summary: Turkish Dependency Parser
Home-page: https://github.com/StarlangSoftware/TurkishDependencyParser-Cy
Author: olcaytaner
Author-email: olcay.yildiz@ozyegin.edu.tr
License-File: LICENSE
Requires-Dist: NlpToolkit-MorphologicalAnalysis-Cy
Dynamic: author
Dynamic: author-email
Dynamic: description
Dynamic: description-content-type
Dynamic: home-page
Dynamic: license-file
Dynamic: requires-dist
Dynamic: summary
